iter_backoff/__init__.py
iter_backoff/test.py
iter_backoff-0.0.0.dist-info/METADATA
iter_backoff-0.0.0.dist-info/WHEEL
iter_backoff-0.0.0.dist-info/top_level.txt
iter_backoff-0.0.0.dist-info/RECORD
